laminci/__init__.py
laminci/__main__.py
laminci/_artifacts.py
laminci/_db.py
laminci/_doc_changes.py
laminci/_docs.py
laminci/_env.py
laminci/_nox_logger.py
laminci/db.py
laminci/nox.py
laminci-0.14.0.dist-info/entry_points.txt
laminci-0.14.0.dist-info/WHEEL
laminci-0.14.0.dist-info/METADATA
laminci-0.14.0.dist-info/RECORD
